django_tropipy/__init__.py
django_tropipy/admin.py
django_tropipy/apps.py
django_tropipy/common.py
django_tropipy/models.py
django_tropipy/tests.py
django_tropipy/urls.py
django_tropipy/views.py
django_tropipy/migrations/0001_initial.py
django_tropipy/migrations/__init__.py
django_tropipy-1.0.3.dist-info/LICENSE
django_tropipy-1.0.3.dist-info/METADATA
django_tropipy-1.0.3.dist-info/WHEEL
django_tropipy-1.0.3.dist-info/top_level.txt
django_tropipy-1.0.3.dist-info/RECORD
