Metadata-Version: 2.1
Name: django-tropipy
Version: 1.0.3
Summary: Easy to use package for processing payments @ www.tropipay.com
Home-page: https://github.com/LhTBL/django-tropipy
Author: Mario Javier Tamayo Marrero, Roberto Sotolongo Fernández
Author-email: Mario Javier Tamayo Marrero <mario.tamayo@lighthousetech.io>, Roberto Sotolongo Fernández <robertosotolongo01@gmail.com>
License: text: GNU General Public License v3 (GPLv3)
Project-URL: Homepage, https://github.com/LhTBL/django-tropipy/
Project-URL: Issues, https://github.com/LhTBL/django-tropipy/issues
Keywords: django,cuba,tropipay
Classifier: Programming Language :: Python :: 3
Classifier: License :: OSI Approved :: MIT License
Classifier: Operating System :: OS Independent
Requires-Python: >=3.8
License-File: LICENSE
